LICENSE
tesseract_decoder.so
tesseract_decoder-0.1.1.dev20260109233451.dist-info/WHEEL
tesseract_decoder-0.1.1.dev20260109233451.dist-info/METADATA
tesseract_decoder-0.1.1.dev20260109233451.dist-info/RECORD
