Metadata-Version: 2.1
Name: tesseract_decoder
Author: The Tesseract Decoder Authors.
Home-page: https://github.com/quantumlib/tesseract-decoder
License: Apache 2
Summary: A search-based decoder for quantum error correction (QEC).
Requires-Dist: stim
Version: 0.1.1.dev20260109233451
